tests/__init__.py
tests/test_abi.py
tests/test_client.py
tests/test_contract.py
tests/test_keys.py
tests/test_query.py
tests/utils.py
tronpy3/__init__.py
tronpy3/abi.py
tronpy3/async_contract.py
tronpy3/async_tron.py
tronpy3/contract.py
tronpy3/defaults.py
tronpy3/exceptions.py
tronpy3/tron.py
tronpy3/version.py
tronpy3/hdwallet/__init__.py
tronpy3/hdwallet/_utils.py
tronpy3/hdwallet/deterministic.py
tronpy3/keys/__init__.py
tronpy3/providers/__init__.py
tronpy3/providers/async_http.py
tronpy3/providers/http.py
tronpy3-1.0.7.dist-info/LICENSE
tronpy3-1.0.7.dist-info/METADATA
tronpy3-1.0.7.dist-info/WHEEL
tronpy3-1.0.7.dist-info/top_level.txt
tronpy3-1.0.7.dist-info/RECORD
