Metadata-Version: 2.1
Name: tronpy3
Version: 1.0.7
Summary: A small example package
Home-page: 
Author: mikezhou_talk
Author-email: 
License: BSD License
Platform: all
Classifier: Intended Audience :: Developers
Classifier: Operating System :: OS Independent
Classifier: Natural Language :: Chinese (Simplified)
Classifier: Programming Language :: Python
Classifier: Programming Language :: Python :: 2
Classifier: Programming Language :: Python :: 2.7
Classifier: Programming Language :: Python :: 3
Classifier: Programming Language :: Python :: 3.5
Classifier: Programming Language :: Python :: 3.6
Classifier: Programming Language :: Python :: 3.7
Classifier: Programming Language :: Python :: 3.8
Classifier: Topic :: Software Development :: Libraries
License-File: LICENSE
Requires-Dist: base58
Requires-Dist: coincurve
Requires-Dist: eth-abi <6.0.0,>=5.0.0
Requires-Dist: httpx
Requires-Dist: pycryptodome <4
Requires-Dist: requests
